schoolschedulerapp/Makefile
schoolschedulerapp/SchoolScheduler.db
schoolschedulerapp/__init__.py
schoolschedulerapp/db.py
schoolschedulerapp/db_alchemy.py
schoolschedulerapp/edit.png
schoolschedulerapp/generatedata.py
schoolschedulerapp/main.py
schoolschedulerapp/sa.so
schoolschedulerapp/schedule.py
schoolschedulerapp/scheduler.rs
schoolschedulerapp/scheduler.ui
schoolschedulerapp/schedulerui.py
schoolschedulerapp/search.png
schoolschedulerapp/square.png
schoolschedulerapp/words.txt
schoolschedulerapp/wsl.py
schoolschedulerapp/export/Default PDF Export Directory
schoolschedulerapp/import/Data.xlsx
schoolschedulerapp/import/Test Data Generator Output Directory
schoolschedulerapp/scheduler/SchoolScheduler.db
schoolschedulerapp/venv/pyvenv.cfg
SchoolSchedulerApp-2.0.2.dist-info/METADATA
SchoolSchedulerApp-2.0.2.dist-info/WHEEL
SchoolSchedulerApp-2.0.2.dist-info/entry_points.txt
SchoolSchedulerApp-2.0.2.dist-info/top_level.txt
SchoolSchedulerApp-2.0.2.dist-info/RECORD
