Metadata-Version: 2.1
Name: SchoolSchedulerApp
Version: 2.0.2
Summary: Python School Scheduler
Home-page: https://github.com/jaberrio/SchoolScheduler
Author: Julian Berrio, Megan Quinn, Navid Ali, Justin Miller, Michael Berry
Author-email: miller.j@ufl.edu
License: UNKNOWN
Project-URL: Source, https://github.com/jaberrio/SchoolScheduler
Project-URL: Bug Tracker, https://trello.com/b/G1f61mAc/school-scheduler
Platform: UNKNOWN
Requires-Dist: PyQt5
Requires-Dist: reportlab
Requires-Dist: sqlalchemy
Requires-Dist: openpyxl
Requires-Dist: xlsxwriter
